tcsolver/__init__.py
tcsolver/image_utility.py
tcsolver/silder.py
tcsolver-0.0.4.dist-info/METADATA
tcsolver-0.0.4.dist-info/WHEEL
tcsolver-0.0.4.dist-info/RECORD
