Metadata-Version: 2.4
Name: tcsolver
Version: 0.0.4
Requires-Dist: build>=1.3.0
Requires-Dist: numpy>=2.2.6
Requires-Dist: opencv-python>=4.12.0.88
Requires-Dist: pandas>=2.3.3
Requires-Dist: playwright>=1.56.0
